{
  "data": [
    {
      "id": "MDEwOlJlcG9zaXRvcnkyMDkwMjc4NDM=",
      "name": "UnityPhysicsSimulator",
      "createdAt": "2019-09-17T10:45:19Z",
      "url": "https://github.com/ttvpro007/UnityPhysicsSimulator",
      "description": null,
      "isFork": false,
      "languages": [
        {
          "name": "C#",
          "iconifyClass": "logos-c-sharp"
        }
      ]
    },
    {
      "id": "MDEwOlJlcG9zaXRvcnkyMjY3NzA2Mjg=",
      "name": "Bull-Cow-Game",
      "createdAt": "2019-12-09T02:47:10Z",
      "url": "https://github.com/ttvpro007/Bull-Cow-Game",
      "description": "GameDev.tv Unreal Engine 4 C++ course content",
      "isFork": false,
      "languages": []
    },
    {
      "id": "MDEwOlJlcG9zaXRvcnkyMTM5MzEyOTI=",
      "name": "Catavaneer-Redo",
      "createdAt": "2019-10-09T13:50:15Z",
      "url": "https://github.com/ttvpro007/Catavaneer-Redo",
      "description": null,
      "isFork": false,
      "languages": [
        {
          "name": "C#",
          "iconifyClass": "logos-c-sharp"
        }
      ]
    },
    {
      "id": "MDEwOlJlcG9zaXRvcnkyMTkyMDUzNTU=",
      "name": "Planet-Runner",
      "createdAt": "2019-11-02T19:45:53Z",
      "url": "https://github.com/ttvpro007/Planet-Runner",
      "description": null,
      "isFork": false,
      "languages": [
        {
          "name": "C#",
          "iconifyClass": "logos-c-sharp"
        },
        {
          "name": "HTML",
          "iconifyClass": "logos-html-5"
        },
        {
          "name": "CSS",
          "iconifyClass": "logos-css-3"
        }
      ]
    },
    {
      "id": "MDEwOlJlcG9zaXRvcnkzMjMyMzEwNTE=",
      "name": "Programming-Problems-Solution",
      "createdAt": "2020-12-21T04:34:26Z",
      "url": "https://github.com/ttvpro007/Programming-Problems-Solution",
      "description": "Collection of programming problems on Codewars and solutions",
      "isFork": false,
      "languages": [
        {
          "name": "C#",
          "iconifyClass": "logos-c-sharp"
        }
      ]
    }
  ]
}
